networking_dpm/__init__.py
networking_dpm/version.py
networking_dpm/cmd/__init__.py
networking_dpm/cmd/eventlet/__init__.py
networking_dpm/cmd/eventlet/dpm_neutron_agent.py
networking_dpm/conf/__init__.py
networking_dpm/conf/cfg.py
networking_dpm/conf/config.py
networking_dpm/conf/types.py
networking_dpm/ml2/__init__.py
networking_dpm/ml2/constants.py
networking_dpm/ml2/dpm_neutron_agent.py
networking_dpm/ml2/mech_dpm.py
networking_dpm/tests/__init__.py
networking_dpm/tests/base.py
networking_dpm/tests/unit/__init__.py
networking_dpm/tests/unit/fake_zhmcclient.py
networking_dpm/tests/unit/test_fake_zhmcclient.py
networking_dpm/tests/unit/conf/__init__.py
networking_dpm/tests/unit/conf/test_cfg.py
networking_dpm/tests/unit/conf/test_config.py
networking_dpm/tests/unit/conf/test_types.py
networking_dpm/tests/unit/ml2/__init__.py
networking_dpm/tests/unit/ml2/test_dpm_neutron_agent.py
networking_dpm/tests/unit/ml2/test_mech_dpm.py
networking_dpm-3.0.0.dist-info/DESCRIPTION.rst
networking_dpm-3.0.0.dist-info/METADATA
networking_dpm-3.0.0.dist-info/RECORD
networking_dpm-3.0.0.dist-info/WHEEL
networking_dpm-3.0.0.dist-info/entry_points.txt
networking_dpm-3.0.0.dist-info/metadata.json
networking_dpm-3.0.0.dist-info/pbr.json
networking_dpm-3.0.0.dist-info/top_level.txt
