Metadata-Version: 2.0
Name: networking-dpm
Version: 3.0.0
Summary: OpenStack Neutron mechanism driver and agent for IBM z Systems PR/SM hypervisor in DPM mode
Home-page: https://www.openstack.org/
Author: OpenStack
Author-email: openstack-dev@lists.openstack.org
License: UNKNOWN
Platform: UNKNOWN
Classifier: Environment :: OpenStack
Classifier: Intended Audience :: Information Technology
Classifier: Intended Audience :: System Administrators
Classifier: License :: OSI Approved :: Apache Software License
Classifier: Operating System :: POSIX :: Linux
Classifier: Programming Language :: Python
Classifier: Programming Language :: Python :: 2
Classifier: Programming Language :: Python :: 2.7
Classifier: Programming Language :: Python :: 3
Classifier: Programming Language :: Python :: 3.3
Classifier: Programming Language :: Python :: 3.5
Requires-Dist: pbr (!=2.1.0,>=2.0.0)
Requires-Dist: os-dpm (>=1.0.0)
Requires-Dist: oslo.config (>=4.6.0)
Requires-Dist: oslo.log (>=3.30.0)
Requires-Dist: oslo.messaging (>=5.29.0)
Requires-Dist: oslo.service (>=1.24.0)
Requires-Dist: oslo.utils (>=3.28.0)
Requires-Dist: requests (>=2.14.2)
Requires-Dist: zhmcclient (>=0.9.0)
